centesimal_iot-0.1.25.dist-info/licenses/AUTHORS.rst
iot/__init__.py
iot/cli.py
iot/helpers.py
iot/iot.py
iot/cli/__init__.py
iot/cli/config.py
iot/cli/describe.py
iot/cli/facts.py
iot/cli/get.py
iot/cli/inventory.py
iot/cli/main.py
iot/cli/manifest.py
iot/cli/plan.py
iot/cli/real.py
iot/cli/roles.py
iot/cli/run.py
iot/cli/target.py
iot/cli/test.py
iot/cli/users.py
iot/cli/watch.py
iot/cli/wingdbstub.py
iot/cli/workspaces.py
iot/tools/__init__.py
iot/tools/persistence.py
centesimal_iot-0.1.25.dist-info/METADATA
centesimal_iot-0.1.25.dist-info/WHEEL
centesimal_iot-0.1.25.dist-info/entry_points.txt
centesimal_iot-0.1.25.dist-info/top_level.txt
centesimal_iot-0.1.25.dist-info/RECORD
