Metadata-Version: 2.4
Name: centesimal_iot
Version: 0.1.25
Summary: IoT infrastructure
Home-page: https://github.com/asterio.gonzalez/iot
Author: Asterio Gonzalez
Author-email: apastor@cibernos.com
Keywords: iot
Classifier: Development Status :: 2 - Pre-Alpha
Classifier: Intended Audience :: Developers
Classifier: Natural Language :: English
Classifier: Programming Language :: Python :: 3
Classifier: Programming Language :: Python :: 3.6
Classifier: Programming Language :: Python :: 3.7
Classifier: Programming Language :: Python :: 3.8
Classifier: Programming Language :: Python :: 3.9
Classifier: Programming Language :: Python :: 3.10
Classifier: Programming Language :: Python :: 3.11
Requires-Python: >=3.6
License-File: AUTHORS.rst
Requires-Dist: Click>=7.0
Requires-Dist: pycelium
Dynamic: author
Dynamic: author-email
Dynamic: classifier
Dynamic: description
Dynamic: home-page
Dynamic: keywords
Dynamic: license-file
Dynamic: requires-dist
Dynamic: requires-python
Dynamic: summary
